whataspp_inforu_local/WhatsAppLocalConstants.py
whataspp_inforu_local/WhatsAppMessageInforuLocal.py
whataspp_inforu_local/__init__.py
whataspp_inforu_local-0.0.13.dist-info/METADATA
whataspp_inforu_local-0.0.13.dist-info/WHEEL
whataspp_inforu_local-0.0.13.dist-info/top_level.txt
whataspp_inforu_local-0.0.13.dist-info/RECORD
