Metadata-Version: 2.1
Name: whataspp-inforu-local
Version: 0.0.13
Summary: PyPI Package for Circles whataspp_inforu_local Python
Home-page: https://github.com/circles-zone/whatsapp-message-inforu-local-python-package
Author: Circles
Author-email: info@circlez.ai
Classifier: Programming Language :: Python :: 3
Classifier: License :: Other/Proprietary License
Classifier: Operating System :: OS Independent
Requires-Dist: requests >=2.31.0
Requires-Dist: logger-local >=0.0.135
Requires-Dist: message-local >=0.0.122
Requires-Dist: python-sdk-remote >=0.0.93
